{
  "figure_no": 51,
  "figure_id": "Figure 51",
  "api_page": 176,
  "pdf_page": 184,
  "caption_original": "Figure 51—Rodding Tee’s",
  "caption_ru": "Рисунок 51 — Тройники для прочистки",
  "stage4_status": "accepted",
  "approval_status": "approved",
  "approval_basis": "accepted by user on 2026-07-01 after PDF-source rebuild review; do not modify this figure further without explicit reopening",
  "source_policy": "rebuilt from original API 551 2016 (R2024).pdf page 184; approved translations preserved; no OCR-derived decisions used",
  "source_pdf_link": "../../../source/API%20551%202016%20(R2024).pdf#page=184",
  "source_pdf_sha256_local": "d458b3a899902f216767e753aa5737a9745b61adcab02f85c9521937a9d3e270",
  "source_crop": "figure_051.source_crop.png",
  "source_crop_sha256": "815f55bb6f5930238cfdb7e1b98784d068dbe2c5d9e35b87415ec45a632dc337",
  "png_file": "figure_051.png",
  "translated_review_png_sha256": "41f2a804a8f0adf7dbc4639e23dee3c38d46ecfba908b10cc6b8a5aa18f0313d",
  "font": "/usr/share/fonts/opentype/urw-base35/NimbusSans-Regular.otf",
  "render_scale": 3.0,
  "crop_pdf_points": {
    "source_crop": [
      100.0,
      80.0,
      520.0,
      535.0
    ],
    "final_png": [
      100.0,
      80.0,
      520.0,
      508.0
    ]
  },
  "visual_label_blocks": [
    {
      "label_block_no": 1,
      "original_text": "Provide clearance for rodout device 760 mm (30 in.) or more",
      "ru_text": "Предусмотреть свободное пространство для устройства прочистки 760 мм (30″) или более",
      "source_text_rect_pdf": [
        266.5,
        101.5,
        412.5,
        123.8
      ],
      "placement_rect_pdf": [
        262.0,
        87.0,
        417.0,
        136.0
      ],
      "render": {
        "cleanup_rect_px": [
          492,
          56,
          946,
          139
        ],
        "box_px": [
          486,
          21,
          951,
          168
        ],
        "lines": [
          "Предусмотреть свободное",
          "пространство для устройства",
          "прочистки 760 мм",
          "(30″) или более"
        ],
        "font_size_px": 23,
        "text_boxes_px": [
          [
            576,
            42,
            861,
            65
          ],
          [
            560,
            69,
            876,
            91
          ],
          [
            623,
            95,
            814,
            117
          ],
          [
            635,
            121,
            801,
            144
          ]
        ]
      },
      "status": "accepted"
    },
    {
      "label_block_no": 2,
      "original_text": "Rodout tee",
      "ru_text": "Тройник для прочистки",
      "source_text_rect_pdf": [
        193.5,
        408.8,
        240.0,
        420.5
      ],
      "placement_rect_pdf": [
        153.0,
        398.0,
        242.0,
        429.0
      ],
      "render": {
        "cleanup_rect_px": [
          272,
          978,
          428,
          1030
        ],
        "box_px": [
          159,
          954,
          426,
          1047
        ],
        "lines": [
          "Тройник для",
          "прочистки"
        ],
        "font_size_px": 23,
        "text_boxes_px": [
          [
            226,
            978,
            358,
            1000
          ],
          [
            238,
            1004,
            346,
            1021
          ]
        ]
      },
      "status": "accepted"
    },
    {
      "label_block_no": 3,
      "original_text": "Blowback valve",
      "ru_text": "Клапан обратной продувки",
      "source_text_rect_pdf": [
        223.2,
        467.2,
        288.0,
        479.0
      ],
      "placement_rect_pdf": [
        191.0,
        456.0,
        291.5,
        491.0
      ],
      "render": {
        "cleanup_rect_px": [
          362,
          1154,
          572,
          1205
        ],
        "box_px": [
          273,
          1128,
          574,
          1233
        ],
        "lines": [
          "Клапан обратной",
          "продувки"
        ],
        "font_size_px": 23,
        "text_boxes_px": [
          [
            331,
            1157,
            515,
            1180
          ],
          [
            374,
            1184,
            472,
            1201
          ]
        ]
      },
      "status": "accepted"
    }
  ],
  "protected_policy": {
    "preserved": [
      "leader lines",
      "arrows",
      "vessel outline",
      "piping/instrument geometry",
      "dimension arrows and extension lines",
      "bottom manifold drawing"
    ],
    "dimension_values_handling": "760 mm / 30 in. preserved semantically in translation, not inferred from OCR"
  },
  "qa": {
    "source": "original PDF page 184 rendered directly",
    "label_count": 3,
    "original_english_removed_from_replaced_label_regions": true,
    "boxed_callout_rule": "gray outline only; white interior; no solid gray fill",
    "out_html_clean": true,
    "object_html_service": true,
    "status_consistency": "object files/catalog mark accepted after user approval on 2026-07-01"
  },
  "ready_for_final_export": true,
  "do_not_touch_after_approval": true,
  "status": "accepted",
  "accepted_from_status": "измененно_2026-07-01",
  "accepted_on": "2026-07-01"
}
